subio/__init__.py
subio/__main__.py
subio/const.py
subio/config/__init__.py
subio/config/model.py
subio/docgen/docgen.py
subio/log/log.py
subio/mapgen/genmap.py
subio/nodefilter/filter.py
subio/tools/tools.py
subio/transform/node.py
subio/transform/ruleset.py
subio/transform/transform.py
subio/transform/validate.py
subio/unify/parse.py
subio/unify/tools.py
subio/unify/parser/clash.py
subio/unify/parser/common.py
subio/unify/parser/dae.py
subio/unify/parser/surge.py
subio/unify/parser/v2rayn.py
subio/upload/upload.py
subio-0.1.0.dist-info/METADATA
subio-0.1.0.dist-info/WHEEL
subio-0.1.0.dist-info/entry_points.txt
subio-0.1.0.dist-info/top_level.txt
subio-0.1.0.dist-info/RECORD
