Metadata-Version: 2.1
Name: subio
Version: 0.1.0
Summary: A simple command line tool for convert proxy subscription links.
Author-email: EkkoG <beijiu572@gmail.com>
Requires-Dist: requests
Requires-Dist: Jinja2 >=3.1.2
Requires-Dist: dacite
Requires-Dist: toml >=0.10.2
Provides-Extra: json5
Requires-Dist: json5 >=0.9.6 ; extra == 'json5'
Provides-Extra: yaml
Requires-Dist: pyyaml >=5.4.1 ; extra == 'yaml'
